temporal_redis/__init__.py
temporal_redis/temporal_redis.py
temporal_redis-0.4.dist-info/METADATA
temporal_redis-0.4.dist-info/WHEEL
temporal_redis-0.4.dist-info/top_level.txt
temporal_redis-0.4.dist-info/RECORD
