Metadata-Version: 2.4
Name: temporal_redis
Version: 0.4
Summary: Temporal workflow result storage in Redis with TTL, retry, and batching
Author-email: Your Name <you@example.com>
License: MIT
Requires-Python: >=3.10
Requires-Dist: temporalio>=1.0.0
Requires-Dist: redis>=4.6.0
Requires-Dist: pydantic>=2.0.0
Requires-Dist: orjson>=3.9.0
Requires-Dist: tenacity>=8.0.0
